signnow_smolagents-0.1.5.dist-info/licenses/LICENSE
sn_smolagent_tools_demo/__init__.py
signnow_smolagents-0.1.5.dist-info/METADATA
signnow_smolagents-0.1.5.dist-info/WHEEL
signnow_smolagents-0.1.5.dist-info/top_level.txt
signnow_smolagents-0.1.5.dist-info/RECORD
