Metadata-Version: 2.4
Name: signnow-smolagents
Version: 0.1.5
Summary: SmolAgents tools for SignNow API integration
Author-email: Lebedev Mikhail <mihasichechek@gmail.com>
License: MIT
Project-URL: Homepage, https://github.com/mihasicehcek/sn_smolagent_tools_demo
Classifier: Programming Language :: Python :: 3
Classifier: License :: OSI Approved :: MIT License
Classifier: Operating System :: OS Independent
License-File: LICENSE
Requires-Dist: requests
Requires-Dist: smolagents
Dynamic: license-file
